dirscribe/__init__.py
dirscribe/core.py
dirscribe-0.1.3.dist-info/LICENSE
dirscribe-0.1.3.dist-info/METADATA
dirscribe-0.1.3.dist-info/WHEEL
dirscribe-0.1.3.dist-info/entry_points.txt
dirscribe-0.1.3.dist-info/top_level.txt
dirscribe-0.1.3.dist-info/RECORD
