Metadata-Version: 2.2
Name: dirscribe
Version: 0.1.3
Summary: A tool to export directory structure and optionally include file contents for selected extensions.
Home-page: https://github.com/kkwmr/dirscribe
Author: Kazuki Kawamura
License: MIT
Classifier: Programming Language :: Python :: 3
Classifier: License :: OSI Approved :: MIT License
Classifier: Operating System :: OS Independent
Requires-Python: >=3.7
License-File: LICENSE
Requires-Dist: pyperclip
Dynamic: author
Dynamic: classifier
Dynamic: description
Dynamic: description-content-type
Dynamic: home-page
Dynamic: license
Dynamic: requires-dist
Dynamic: requires-python
Dynamic: summary
